searchtweets/__init__.py
searchtweets/_version.py
searchtweets/api_utils.py
searchtweets/credentials.py
searchtweets/result_stream.py
searchtweets/utils.py
searchtweets-1.7.6.data/scripts/poll_tweets.py
searchtweets-1.7.6.data/scripts/search_tweets.py
searchtweets-1.7.6.dist-info/LICENSE
searchtweets-1.7.6.dist-info/METADATA
searchtweets-1.7.6.dist-info/WHEEL
searchtweets-1.7.6.dist-info/top_level.txt
searchtweets-1.7.6.dist-info/RECORD
