Metadata-Version: 1.2
Name: searchtweets
Version: 1.7.6
Summary: Wrapper for Twitter's Premium and Enterprise search APIs
Home-page: https://github.com/twitterdev/search-tweets-python
Author: Fiona Pigott, Jeff Kolb, Josh Montague, Aaron Gonzales
Author-email: agonzales@twitter.com
License: MIT
Platform: UNKNOWN
Requires-Python: >=3.3
